whit-phys-util/__init__.py
whit-phys-util/pretty_fit.py
whit-phys-util/git_access/__init__.py
whit-phys-util/git_access/_git_access.py
whit-phys-util/git_access/git_settings.py
whit-phys-util/git_access/run_cmd.py
whit_phys_util/__init__.py
whit_phys_util/_version.py
whit_phys_util/create_pdf.py
whit_phys_util/dynamic_data_entry.py
whit_phys_util/pretty_fit.py
whit_phys_util/git_access/__init__.py
whit_phys_util/git_access/_git_access.py
whit_phys_util/git_access/_git_settings.py
whit_phys_util/git_access/_run_cmd.py
whit_phys_util/git_access/git_settings.py
whit_phys_util/git_access/run_cmd.py
whit_phys_util-1.1.0.dist-info/LICENSE
whit_phys_util-1.1.0.dist-info/METADATA
whit_phys_util-1.1.0.dist-info/WHEEL
whit_phys_util-1.1.0.dist-info/top_level.txt
whit_phys_util-1.1.0.dist-info/RECORD
