Metadata-Version: 2.1
Name: whit-phys-util
Version: 1.1.0
Summary: Tools to support use of Google Colab + GitHub Classroom for physics lab instruction
Home-page: https://github.com/JohnMLarkin/Colab-for-Physics-Lab-Tools
Author: John Larkin
Author-email: jlarkin@whitworth.edu
License: UNKNOWN
Platform: UNKNOWN
Classifier: Programming Language :: Python :: 3
Classifier: License :: OSI Approved :: MIT License
Classifier: Operating System :: OS Independent
Requires-Python: >=3.10
Requires-Dist: ipydatagrid (>=1.3.2)
Requires-Dist: pydantic-settings (>=2.4.0)
